python_gce_logging-0.2.dist-info/METADATA
python_gce_logging-0.2.dist-info/RECORD
python_gce_logging-0.2.dist-info/WHEEL
python_gce_logging-0.2.dist-info/top_level.txt
pythongcelogging/__init__.py
